<?xml version="1.0" encoding="UTF-8"?>
<MF0 version="1.1" packageUris="http://schema.mathworks.com/mf0/ci/19700101 http://schema.mathworks.com/mf0/sl_modelref_info/R2024b http://schema.mathworks.com/mf0/slexec_mm_sto/R2024a_202305081229 http://schema.mathworks.com/mf0/sltp_mm/R2024b_202402211119">
  <ModelRefInfoRepo.ModelRefInfoRoot type="ModelRefInfoRepo.ModelRefInfoRoot" uuid="ba0b86c7-7176-498a-a9bf-d2041c7c1842">
    <JITEngines>sjT7pRcYU9XPTLAaCgVumB</JITEngines>
    <JITEngines>sxMu0A5tkHjoD7fnhr6cDVC</JITEngines>
    <childModelRefInfo type="ModelRefInfoRepo.ChildModelRefInfo" uuid="31f9890d-db50-480d-a633-89115ab91904">
      <modelName>HT09_Linear_Vehicle_Model</modelName>
      <modelPath>HT09_Linear_Vehicle_Model</modelPath>
    </childModelRefInfo>
    <compDerivCacheNeedsReset>false</compDerivCacheNeedsReset>
    <compZcCacheNeedsReset>false</compZcCacheNeedsReset>
    <compiledTFinal>15.0</compiledTFinal>
    <dataSourceInfo type="ModelRefInfoRepo.DataSourceInfo" uuid="79935f4f-c4a3-4251-9c5a-d21b0f6a476e">
      <dataSources type="ModelRefInfoRepo.SourceInfo" uuid="ae5e306e-8ace-4119-a751-cf3070325cdf">
        <includeAllSections>true</includeAllSections>
        <sourceName>base workspace</sourceName>
        <type>BaseWorkspace</type>
      </dataSources>
      <modelName>HT09_Linear_Vehicle_Model</modelName>
    </dataSourceInfo>
    <dataTransferInfos>AAFJTQAAAAAOAAAAOAAAAAYAAAAIAAAAAgAAAAAAAAAFAAAACAAAAAAAAAABAAAAAQAAAAAAAAAFAAQAAQAAAAEAAAAAAAAA</dataTransferInfos>
    <discStateRecordInfo type="ModelRefInfoRepo.StateRecordInfo" uuid="63d89315-c100-4e29-88a9-12dc39206445">
      <blockName>HT09_Linear_Vehicle_Model/Discrete Varying State Space/State</blockName>
      <crossMdlRef>true</crossMdlRef>
      <label>DSTATE</label>
      <width>2</width>
    </discStateRecordInfo>
    <fastestNoncontSigFeedingDerivPorts>-1.0</fastestNoncontSigFeedingDerivPorts>
    <fundamentalSampleTimePeriod>.001</fundamentalSampleTimePeriod>
    <globalVariables>Iz_vehicle</globalVariables>
    <globalVariables>LM</globalVariables>
    <globalVariables>dt</globalVariables>
    <globalVariables>lf</globalVariables>
    <globalVariables>lr</globalVariables>
    <globalVariables>m</globalVariables>
    <globalVariables>wb</globalVariables>
    <grCompInputPortMaps>0,0,0;1,1,1;2,2,2;3,3,3;4,4,4;5,5,5;6,6,6</grCompInputPortMaps>
    <grCompOutputPortMaps>0,0,5;1,6,6;2,7,7;3,8,8;4,9,9</grCompOutputPortMaps>
    <hasBlockWithPeriodicDiscreteSampleTime>true</hasBlockWithPeriodicDiscreteSampleTime>
    <hasBwsAccessed>true</hasBwsAccessed>
    <hasConstantOutput>true</hasConstantOutput>
    <hasModelWideEventTs>false</hasModelWideEventTs>
    <hasNonVirtualConstantTs>true</hasNonVirtualConstantTs>
    <inlinedVariables>Iz_vehicle</inlinedVariables>
    <inlinedVariables>LM</inlinedVariables>
    <inlinedVariables>dt</inlinedVariables>
    <inlinedVariables>lf</inlinedVariables>
    <inlinedVariables>lr</inlinedVariables>
    <inlinedVariables>m</inlinedVariables>
    <inlinedVariables>wb</inlinedVariables>
    <inports type="ModelRefInfoRepo.InportInformation" uuid="9a6181ef-db64-409f-beb2-3d12c558bb23">
      <globalInRTW>false</globalInRTW>
      <isNotDerivPort>true</isNotDerivPort>
      <overWritable>false</overWritable>
      <designMax>inf</designMax>
      <designMin>-inf</designMin>
      <indexType>2</indexType>
      <rateInfos type="ModelRefInfoRepo.RateInfo">
        <compiled>true</compiled>
        <nonFcnCallPartitionName>D1</nonFcnCallPartitionName>
        <period>.001</period>
        <priority>40</priority>
        <rateIdx>0</rateIdx>
      </rateInfos>
      <resolvedSignalObject></resolvedSignalObject>
      <executionInterface type="ModelRefInfoRepo.InputExecutionInterface" uuid="9c1d5d6f-dda6-41a7-b9d2-8043ced422e3"/>
      <sigNameToEMVCEMap type="ModelRefInfoRepo.SigNameEMVCEInfo" uuid="79c6836f-d394-42e4-a43e-5558d24e240c"/>
    </inports>
    <inports type="ModelRefInfoRepo.InportInformation" uuid="319b0da1-9c0d-434f-ae1c-ab7c91c7cb6f">
      <globalInRTW>false</globalInRTW>
      <isNotDerivPort>true</isNotDerivPort>
      <notReusable>false</notReusable>
      <overWritable>false</overWritable>
      <designMax>inf</designMax>
      <designMin>-inf</designMin>
      <indexType>2</indexType>
      <originalPortNumber>1</originalPortNumber>
      <rateInfos type="ModelRefInfoRepo.RateInfo">
        <compiled>true</compiled>
        <nonFcnCallPartitionName>D1</nonFcnCallPartitionName>
        <period>.001</period>
        <priority>40</priority>
        <rateIdx>0</rateIdx>
      </rateInfos>
      <resolvedSignalObject></resolvedSignalObject>
      <executionInterface type="ModelRefInfoRepo.InputExecutionInterface" uuid="880f22b7-39d1-4636-ba86-40a27835d541"/>
      <sigNameToEMVCEMap type="ModelRefInfoRepo.SigNameEMVCEInfo" uuid="c921fca8-4f2b-4d91-85f8-0af1b772943e"/>
    </inports>
    <inports type="ModelRefInfoRepo.InportInformation" uuid="110e1d2b-9bc5-4bb5-ab29-7020a30d6d84">
      <globalInRTW>false</globalInRTW>
      <isNotDerivPort>true</isNotDerivPort>
      <notReusable>false</notReusable>
      <overWritable>false</overWritable>
      <designMax>inf</designMax>
      <designMin>-inf</designMin>
      <indexType>2</indexType>
      <originalPortNumber>2</originalPortNumber>
      <rateInfos type="ModelRefInfoRepo.RateInfo">
        <compiled>true</compiled>
        <nonFcnCallPartitionName>D1</nonFcnCallPartitionName>
        <period>.001</period>
        <priority>40</priority>
        <rateIdx>0</rateIdx>
      </rateInfos>
      <resolvedSignalObject></resolvedSignalObject>
      <executionInterface type="ModelRefInfoRepo.InputExecutionInterface" uuid="9909da19-1387-4693-87e5-7a46bf2f082e"/>
      <sigNameToEMVCEMap type="ModelRefInfoRepo.SigNameEMVCEInfo" uuid="ad2989cc-0498-4930-84a7-cc6cd068edfe"/>
    </inports>
    <inports type="ModelRefInfoRepo.InportInformation" uuid="abd50256-fe23-4073-b23e-43c1656b3b29">
      <globalInRTW>false</globalInRTW>
      <isNotDerivPort>true</isNotDerivPort>
      <notReusable>false</notReusable>
      <overWritable>false</overWritable>
      <designMax>inf</designMax>
      <designMin>-inf</designMin>
      <indexType>2</indexType>
      <originalPortNumber>3</originalPortNumber>
      <rateInfos type="ModelRefInfoRepo.RateInfo">
        <compiled>true</compiled>
        <nonFcnCallPartitionName>D1</nonFcnCallPartitionName>
        <period>.001</period>
        <priority>40</priority>
        <rateIdx>0</rateIdx>
      </rateInfos>
      <resolvedSignalObject></resolvedSignalObject>
      <executionInterface type="ModelRefInfoRepo.InputExecutionInterface" uuid="06fc2d18-ed31-4bd4-8738-91eed5c271bb"/>
      <sigNameToEMVCEMap type="ModelRefInfoRepo.SigNameEMVCEInfo" uuid="f5b190ca-8484-43c2-a87f-100de064d23e"/>
    </inports>
    <inports type="ModelRefInfoRepo.InportInformation" uuid="54c3fa57-1759-4298-a723-0810c5dbd69d">
      <globalInRTW>false</globalInRTW>
      <isNotDerivPort>true</isNotDerivPort>
      <notReusable>false</notReusable>
      <overWritable>false</overWritable>
      <designMax>inf</designMax>
      <designMin>-inf</designMin>
      <indexType>2</indexType>
      <originalPortNumber>4</originalPortNumber>
      <rateInfos type="ModelRefInfoRepo.RateInfo">
        <compiled>true</compiled>
        <nonFcnCallPartitionName>D1</nonFcnCallPartitionName>
        <period>.001</period>
        <priority>40</priority>
        <rateIdx>0</rateIdx>
      </rateInfos>
      <resolvedSignalObject></resolvedSignalObject>
      <executionInterface type="ModelRefInfoRepo.InputExecutionInterface" uuid="63470159-03cb-4ef5-a570-1bb1a51b8c9c"/>
      <sigNameToEMVCEMap type="ModelRefInfoRepo.SigNameEMVCEInfo" uuid="e58a7df7-f0e8-479e-b03a-41797dc2bb45"/>
    </inports>
    <inports type="ModelRefInfoRepo.InportInformation" uuid="b17a46b9-c06b-4bf0-8a3a-0c003df68952">
      <globalInRTW>false</globalInRTW>
      <isNotDerivPort>true</isNotDerivPort>
      <notReusable>false</notReusable>
      <overWritable>false</overWritable>
      <designMax>inf</designMax>
      <designMin>-inf</designMin>
      <indexType>2</indexType>
      <originalPortNumber>5</originalPortNumber>
      <rateInfos type="ModelRefInfoRepo.RateInfo">
        <compiled>true</compiled>
        <nonFcnCallPartitionName>D1</nonFcnCallPartitionName>
        <period>.001</period>
        <priority>40</priority>
        <rateIdx>0</rateIdx>
      </rateInfos>
      <resolvedSignalObject></resolvedSignalObject>
      <executionInterface type="ModelRefInfoRepo.InputExecutionInterface" uuid="87684090-a7cf-4c59-ae11-dd414aabbfd9"/>
      <sigNameToEMVCEMap type="ModelRefInfoRepo.SigNameEMVCEInfo" uuid="46483af1-f8a0-4871-a9b8-38435e559c1f"/>
    </inports>
    <inports type="ModelRefInfoRepo.InportInformation" uuid="0c6c35ed-3af3-402e-97fb-bd3ae5336669">
      <globalInRTW>false</globalInRTW>
      <isNotDerivPort>true</isNotDerivPort>
      <overWritable>false</overWritable>
      <designMax>inf</designMax>
      <designMin>-inf</designMin>
      <indexType>2</indexType>
      <originalPortNumber>6</originalPortNumber>
      <rateInfos type="ModelRefInfoRepo.RateInfo">
        <compiled>true</compiled>
        <nonFcnCallPartitionName>D1</nonFcnCallPartitionName>
        <period>.001</period>
        <priority>40</priority>
        <rateIdx>0</rateIdx>
      </rateInfos>
      <resolvedSignalObject></resolvedSignalObject>
      <executionInterface type="ModelRefInfoRepo.InputExecutionInterface" uuid="4109f68d-4f80-4f04-9baf-00a6fe56f038"/>
      <sigNameToEMVCEMap type="ModelRefInfoRepo.SigNameEMVCEInfo" uuid="70756077-c92c-4dcd-bae9-2b7fc6887b80"/>
    </inports>
    <invalidPortInfo type="ModelRefInfoRepo.InvalidPortInfo" uuid="f7e5ea33-b88f-4331-b235-e78c927fcc15">
      <messageID>NONCont</messageID>
      <modelName>HT09_Linear_Vehicle_Model</modelName>
      <msgArgs>1</msgArgs>
      <msgArgs>HT09_Linear_Vehicle_Model/Discrete Varying State Space/RSx</msgArgs>
      <msgArgs>7</msgArgs>
      <recActID>Outport_Port</recActID>
      <titleID>NONCont</titleID>
    </invalidPortInfo>
    <invalidPortInfo type="ModelRefInfoRepo.InvalidPortInfo" uuid="d2175589-3da6-4f5e-9cc0-d5d33ecc2ba0">
      <messageID>NONCont</messageID>
      <modelName>HT09_Linear_Vehicle_Model</modelName>
      <msgArgs>1</msgArgs>
      <msgArgs>HT09_Linear_Vehicle_Model/Discrete Varying State Space/RSx</msgArgs>
      <msgArgs>8</msgArgs>
      <recActID>Outport_Port</recActID>
      <titleID>NONCont</titleID>
    </invalidPortInfo>
    <isAperiodicRootFcnCallSystem>false</isAperiodicRootFcnCallSystem>
    <isBdInSimModeForSimCodegenVariants>false</isBdInSimModeForSimCodegenVariants>
    <isInlineParamsOn>true</isInlineParamsOn>
    <isOrigInportVirtualBus>false</isOrigInportVirtualBus>
    <isOrigInportVirtualBus>false</isOrigInportVirtualBus>
    <isOrigInportVirtualBus>false</isOrigInportVirtualBus>
    <isOrigInportVirtualBus>false</isOrigInportVirtualBus>
    <isOrigInportVirtualBus>false</isOrigInportVirtualBus>
    <isOrigInportVirtualBus>false</isOrigInportVirtualBus>
    <isOrigInportVirtualBus>false</isOrigInportVirtualBus>
    <isOrigOutportVirtualBus>true</isOrigOutportVirtualBus>
    <isOrigOutportVirtualBus>false</isOrigOutportVirtualBus>
    <isOrigOutportVirtualBus>false</isOrigOutportVirtualBus>
    <isOrigOutportVirtualBus>false</isOrigOutportVirtualBus>
    <isOrigOutportVirtualBus>false</isOrigOutportVirtualBus>
    <isPreCompSingleRate>false</isPreCompSingleRate>
    <isRefModelConstant>false</isRefModelConstant>
    <isRootFcnCallPortGroupsEmpty>true</isRootFcnCallPortGroupsEmpty>
    <loggingSaveFormat>2</loggingSaveFormat>
    <maxFreqHz>-1.0</maxFreqHz>
    <nonTunableVariables>dt</nonTunableVariables>
    <numDStateRecs>1</numDStateRecs>
    <numDataInputPorts>7</numDataInputPorts>
    <numLoggableDStateRecs>1</numLoggableDStateRecs>
    <numLoggableJacobianDStates>2</numLoggableJacobianDStates>
    <numModelWideEventTs>0</numModelWideEventTs>
    <numPortlessSimulinkFunctionPortGroups>0</numPortlessSimulinkFunctionPortGroups>
    <numRuntimeExportedRates>1</numRuntimeExportedRates>
    <numTs>1</numTs>
    <origInportBusType></origInportBusType>
    <origInportBusType></origInportBusType>
    <origInportBusType></origInportBusType>
    <origInportBusType></origInportBusType>
    <origInportBusType></origInportBusType>
    <origInportBusType></origInportBusType>
    <origInportBusType></origInportBusType>
    <origOutportBusOutputAsStruct>false</origOutportBusOutputAsStruct>
    <origOutportBusOutputAsStruct>false</origOutportBusOutputAsStruct>
    <origOutportBusOutputAsStruct>false</origOutportBusOutputAsStruct>
    <origOutportBusOutputAsStruct>false</origOutportBusOutputAsStruct>
    <origOutportBusOutputAsStruct>false</origOutportBusOutputAsStruct>
    <origOutportBusType></origOutportBusType>
    <origOutportBusType></origOutportBusType>
    <origOutportBusType></origOutportBusType>
    <origOutportBusType></origOutportBusType>
    <origOutportBusType></origOutportBusType>
    <outports type="ModelRefInfoRepo.OutportInformation" uuid="289fead8-5ad9-4f4f-864d-262bd4dc59eb">
      <drivenByBlockOutputPotentiallyNotUpdateAtRunTime>true</drivenByBlockOutputPotentiallyNotUpdateAtRunTime>
      <globalInRTW>false</globalInRTW>
      <notReusable>false</notReusable>
      <okToMerge>3</okToMerge>
      <designMax>inf</designMax>
      <designMin>-inf</designMin>
      <indexType>2</indexType>
      <rateInfos type="ModelRefInfoRepo.RateInfo">
        <compiled>true</compiled>
        <nonFcnCallPartitionName>D1</nonFcnCallPartitionName>
        <period>.001</period>
        <priority>40</priority>
        <rateIdx>0</rateIdx>
      </rateInfos>
      <resolvedSignalObject></resolvedSignalObject>
      <executionInterface type="ModelRefInfoRepo.OutputExecutionInterface" uuid="4bf7959c-740d-49ea-8d7b-3b64c72d7c0e"/>
      <sigNameToEMVCEMap type="ModelRefInfoRepo.SigNameEMVCEInfo" uuid="10066578-30ae-45b4-9f1f-df7d878c8a1f"/>
    </outports>
    <outports type="ModelRefInfoRepo.OutportInformation" uuid="01826d77-d7d4-438b-b473-43d0686deabc">
      <constantOutputValue>           </constantOutputValue>
      <drivenByBlockOutputPotentiallyNotUpdateAtRunTime>true</drivenByBlockOutputPotentiallyNotUpdateAtRunTime>
      <okToMerge>3</okToMerge>
      <designMax>inf</designMax>
      <designMin>-inf</designMin>
      <indexType>2</indexType>
      <rateInfos type="ModelRefInfoRepo.RateInfo">
        <compiled>true</compiled>
        <needAbsoluteTime>true</needAbsoluteTime>
        <offset>inf</offset>
        <period>inf</period>
        <priority>-2147483648</priority>
        <rateIdx>-2</rateIdx>
      </rateInfos>
      <resolvedSignalObject></resolvedSignalObject>
      <executionInterface type="ModelRefInfoRepo.OutputExecutionInterface" uuid="770936ed-bf91-441e-9d1c-cd346bc88d67"/>
      <sigNameToEMVCEMap type="ModelRefInfoRepo.SigNameEMVCEInfo" uuid="dcc570db-d1c0-47c7-9f82-752a2c92f595"/>
    </outports>
    <outports type="ModelRefInfoRepo.OutportInformation" uuid="dbcb13a1-913a-4e79-99dd-7bb420a287d4">
      <drivenByBlockOutputPotentiallyNotUpdateAtRunTime>true</drivenByBlockOutputPotentiallyNotUpdateAtRunTime>
      <globalInRTW>false</globalInRTW>
      <notReusable>false</notReusable>
      <okToMerge>3</okToMerge>
      <designMax>inf</designMax>
      <designMin>-inf</designMin>
      <indexType>2</indexType>
      <rateInfos type="ModelRefInfoRepo.RateInfo">
        <compiled>true</compiled>
        <nonFcnCallPartitionName>D1</nonFcnCallPartitionName>
        <period>.001</period>
        <priority>40</priority>
        <rateIdx>0</rateIdx>
      </rateInfos>
      <resolvedSignalObject></resolvedSignalObject>
      <executionInterface type="ModelRefInfoRepo.OutputExecutionInterface" uuid="653eec15-3e5b-4bf5-ab38-11f945b48966"/>
      <sigNameToEMVCEMap type="ModelRefInfoRepo.SigNameEMVCEInfo" uuid="6f624652-49db-416d-a7ce-9f18512d3424"/>
    </outports>
    <outports type="ModelRefInfoRepo.OutportInformation" uuid="6024ad47-5745-497d-bfb4-8a14dfb07098">
      <constantOutputValue>           </constantOutputValue>
      <drivenByBlockOutputPotentiallyNotUpdateAtRunTime>true</drivenByBlockOutputPotentiallyNotUpdateAtRunTime>
      <okToMerge>3</okToMerge>
      <designMax>inf</designMax>
      <designMin>-inf</designMin>
      <indexType>2</indexType>
      <rateInfos type="ModelRefInfoRepo.RateInfo">
        <compiled>true</compiled>
        <needAbsoluteTime>true</needAbsoluteTime>
        <offset>inf</offset>
        <period>inf</period>
        <priority>-2147483648</priority>
        <rateIdx>-2</rateIdx>
      </rateInfos>
      <resolvedSignalObject></resolvedSignalObject>
      <executionInterface type="ModelRefInfoRepo.OutputExecutionInterface" uuid="137051ad-b298-47c8-99f0-9b7a5b5a603c"/>
      <sigNameToEMVCEMap type="ModelRefInfoRepo.SigNameEMVCEInfo" uuid="e8a9343b-2af5-456e-b21c-d140f0fad2f8"/>
    </outports>
    <outports type="ModelRefInfoRepo.OutportInformation" uuid="d48c738f-90a5-43df-ba07-3ea60172b312">
      <drivenByBlockOutputPotentiallyNotUpdateAtRunTime>true</drivenByBlockOutputPotentiallyNotUpdateAtRunTime>
      <globalInRTW>false</globalInRTW>
      <notReusable>false</notReusable>
      <okToMerge>3</okToMerge>
      <designMax>inf</designMax>
      <designMin>-inf</designMin>
      <indexType>2</indexType>
      <rateInfos type="ModelRefInfoRepo.RateInfo">
        <compiled>true</compiled>
        <nonFcnCallPartitionName>D1</nonFcnCallPartitionName>
        <period>.001</period>
        <priority>40</priority>
        <rateIdx>0</rateIdx>
      </rateInfos>
      <resolvedSignalObject></resolvedSignalObject>
      <executionInterface type="ModelRefInfoRepo.OutputExecutionInterface" uuid="448b3505-2ecb-4f39-8771-463500f1cad9"/>
      <sigNameToEMVCEMap type="ModelRefInfoRepo.SigNameEMVCEInfo" uuid="03e3532a-5ff6-484d-8fe1-253c5ae8ad96"/>
    </outports>
    <outports type="ModelRefInfoRepo.OutportInformation" uuid="6017e5b9-4d86-4f5c-bd18-7a7f8ba8905b">
      <drivenByBlockOutputPotentiallyNotUpdateAtRunTime>true</drivenByBlockOutputPotentiallyNotUpdateAtRunTime>
      <globalInRTW>false</globalInRTW>
      <notReusable>false</notReusable>
      <okToMerge>3</okToMerge>
      <designMax>inf</designMax>
      <designMin>-inf</designMin>
      <indexType>2</indexType>
      <rateInfos type="ModelRefInfoRepo.RateInfo">
        <compiled>true</compiled>
        <nonFcnCallPartitionName>D1</nonFcnCallPartitionName>
        <period>.001</period>
        <priority>40</priority>
        <rateIdx>0</rateIdx>
      </rateInfos>
      <resolvedSignalObject></resolvedSignalObject>
      <executionInterface type="ModelRefInfoRepo.OutputExecutionInterface" uuid="705d6ea7-b5a2-4c1c-9439-dfafc3c86b37"/>
      <sigNameToEMVCEMap type="ModelRefInfoRepo.SigNameEMVCEInfo" uuid="d8eca3fc-a5e6-4578-bbc4-c6a26ab6bdf9"/>
    </outports>
    <outports type="ModelRefInfoRepo.OutportInformation" uuid="471610fc-24a4-48ac-bc0c-aa2661de8af8">
      <globalInRTW>false</globalInRTW>
      <notReusable>false</notReusable>
      <okToMerge>3</okToMerge>
      <designMax>inf</designMax>
      <designMin>-inf</designMin>
      <indexType>2</indexType>
      <originalPortNumber>1</originalPortNumber>
      <rateInfos type="ModelRefInfoRepo.RateInfo">
        <compiled>true</compiled>
        <nonFcnCallPartitionName>D1</nonFcnCallPartitionName>
        <period>.001</period>
        <priority>40</priority>
        <rateIdx>0</rateIdx>
      </rateInfos>
      <resolvedSignalObject></resolvedSignalObject>
      <executionInterface type="ModelRefInfoRepo.OutputExecutionInterface" uuid="212aaba6-52a7-40d1-a51a-429ca71cb0fa"/>
      <sigNameToEMVCEMap type="ModelRefInfoRepo.SigNameEMVCEInfo" uuid="a7da2d0e-6bfa-4ce0-8cab-a38ea4a24ac6"/>
    </outports>
    <outports type="ModelRefInfoRepo.OutportInformation" uuid="e7871c02-02b1-44e4-9fa5-3228b51abb1f">
      <globalInRTW>false</globalInRTW>
      <notReusable>false</notReusable>
      <okToMerge>3</okToMerge>
      <designMax>inf</designMax>
      <designMin>-inf</designMin>
      <indexType>2</indexType>
      <originalPortNumber>2</originalPortNumber>
      <rateInfos type="ModelRefInfoRepo.RateInfo">
        <compiled>true</compiled>
        <nonFcnCallPartitionName>D1</nonFcnCallPartitionName>
        <period>.001</period>
        <priority>40</priority>
        <rateIdx>0</rateIdx>
      </rateInfos>
      <resolvedSignalObject></resolvedSignalObject>
      <executionInterface type="ModelRefInfoRepo.OutputExecutionInterface" uuid="718cef03-1bd0-474e-a88d-0620f0b86152"/>
      <sigNameToEMVCEMap type="ModelRefInfoRepo.SigNameEMVCEInfo" uuid="5e23ee24-e1bd-4063-87cb-0e18a8ba94d8"/>
    </outports>
    <outports type="ModelRefInfoRepo.OutportInformation" uuid="366ce378-0b41-4783-bca1-b3e6216de6bc">
      <globalInRTW>false</globalInRTW>
      <notReusable>false</notReusable>
      <okToMerge>3</okToMerge>
      <designMax>inf</designMax>
      <designMin>-inf</designMin>
      <indexType>2</indexType>
      <originalPortNumber>3</originalPortNumber>
      <rateInfos type="ModelRefInfoRepo.RateInfo">
        <compiled>true</compiled>
        <nonFcnCallPartitionName>D1</nonFcnCallPartitionName>
        <period>.001</period>
        <priority>40</priority>
        <rateIdx>0</rateIdx>
      </rateInfos>
      <resolvedSignalObject></resolvedSignalObject>
      <executionInterface type="ModelRefInfoRepo.OutputExecutionInterface" uuid="d3d51f19-a51a-4939-9e3b-ad11688c7474"/>
      <sigNameToEMVCEMap type="ModelRefInfoRepo.SigNameEMVCEInfo" uuid="a0facf7f-0f1b-4b18-ad49-383a629e1b5d"/>
    </outports>
    <outports type="ModelRefInfoRepo.OutportInformation" uuid="0320fc92-d8c6-4a2a-b979-e75f31af5dc2">
      <globalInRTW>false</globalInRTW>
      <notReusable>false</notReusable>
      <okToMerge>3</okToMerge>
      <designMax>inf</designMax>
      <designMin>-inf</designMin>
      <indexType>2</indexType>
      <originalPortNumber>4</originalPortNumber>
      <rateInfos type="ModelRefInfoRepo.RateInfo">
        <compiled>true</compiled>
        <nonFcnCallPartitionName>D1</nonFcnCallPartitionName>
        <period>.001</period>
        <priority>40</priority>
        <rateIdx>0</rateIdx>
      </rateInfos>
      <resolvedSignalObject></resolvedSignalObject>
      <executionInterface type="ModelRefInfoRepo.OutputExecutionInterface" uuid="0ecd1281-becd-4daa-a6d7-14eeddd10c50"/>
      <sigNameToEMVCEMap type="ModelRefInfoRepo.SigNameEMVCEInfo" uuid="a0c747c6-bc6d-415f-992b-1692e19c154d"/>
    </outports>
    <preCompAllowConstTsOnPorts>true</preCompAllowConstTsOnPorts>
    <preCompAllowPortBasedInTriggeredSS>false</preCompAllowPortBasedInTriggeredSS>
    <removeResetFunc>true</removeResetFunc>
    <runtimeNonFcnCallRateInfos type="ModelRefInfoRepo.RateInfo">
      <compiled>true</compiled>
      <nonFcnCallPartitionName>D1</nonFcnCallPartitionName>
      <period>.001</period>
      <priority>40</priority>
      <rateIdx>0</rateIdx>
    </runtimeNonFcnCallRateInfos>
    <sampleTimeInheritanceRule>2</sampleTimeInheritanceRule>
    <solverStatusFlags>327</solverStatusFlags>
    <timingAndTaskingRegistry>&lt;?xml version=&quot;1.0&quot;?&gt;
&lt;slexec_sto version=&quot;1.1&quot; packageUris=&quot;http://schema.mathworks.com/mf0/slexec_mm_sto/R2024a_202305081229&quot;&gt;
  &lt;sto.Registry type=&quot;sto.Registry&quot; uuid=&quot;0ed22591-6b3a-417a-9e12-eed1209334fb&quot;&gt;
    &lt;executionSpec&gt;Undetermined&lt;/executionSpec&gt;
    &lt;identifier&gt;HT09_Linear_Vehicle_Model&lt;/identifier&gt;
    &lt;clockRegistry type=&quot;sto.ClockRegistry&quot; uuid=&quot;39dd0968-1900-498d-8fe9-5c21fb48bbcf&quot;&gt;
      &lt;clocks type=&quot;sto.Timer&quot; uuid=&quot;c12cfca9-1c8b-4bf0-b908-542f7c5e2e37&quot;&gt;
        &lt;computedFundamentalDiscretePeriod&gt;.001&lt;/computedFundamentalDiscretePeriod&gt;
        &lt;fastestDiscreteRate type=&quot;sto.ClassicPeriodicDiscreteRate&quot; uuid=&quot;e863b85e-aa59-4185-a641-ab7203efc9b2&quot;/&gt;
        &lt;isDefaultTimer&gt;true&lt;/isDefaultTimer&gt;
        &lt;resolution&gt;.001&lt;/resolution&gt;
        &lt;timeAdvanceMode&gt;FixedStep&lt;/timeAdvanceMode&gt;
        &lt;identifier&gt;HT09_Linear_Vehicle_Model::defaultTimer&lt;/identifier&gt;
        &lt;rates type=&quot;sto.ClassicPeriodicDiscreteRate&quot; uuid=&quot;e863b85e-aa59-4185-a641-ab7203efc9b2&quot;&gt;
          &lt;annotation&gt;D1&lt;/annotation&gt;
          &lt;clockId&gt;HT09_Linear_Vehicle_Model::defaultTimer&lt;/clockId&gt;
          &lt;description&gt;Discrete 1&lt;/description&gt;
          &lt;taskId&gt;_task0&lt;/taskId&gt;
          &lt;rateSpec type=&quot;sto.RateSpec&quot; uuid=&quot;c2b9cd90-3b95-4478-ba08-7ee90b76716b&quot;&gt;
            &lt;period&gt;.001&lt;/period&gt;
            &lt;rateType&gt;ClassicPeriodicDiscrete&lt;/rateType&gt;
          &lt;/rateSpec&gt;
        &lt;/rates&gt;
        &lt;baseRate type=&quot;sto.ClassicPeriodicDiscreteRate&quot; uuid=&quot;eee898a5-6c2f-4546-b3de-6e7d7019e40e&quot;&gt;
          &lt;annotation&gt;D1&lt;/annotation&gt;
          &lt;clockId&gt;HT09_Linear_Vehicle_Model::defaultTimer&lt;/clockId&gt;
          &lt;description&gt;Discrete 1&lt;/description&gt;
          &lt;taskId&gt;_task0&lt;/taskId&gt;
          &lt;rateSpec type=&quot;sto.RateSpec&quot; uuid=&quot;bad63d02-4fb6-4c07-8efe-420a09e1a682&quot;&gt;
            &lt;period&gt;.001&lt;/period&gt;
            &lt;rateType&gt;ClassicPeriodicDiscrete&lt;/rateType&gt;
          &lt;/rateSpec&gt;
        &lt;/baseRate&gt;
      &lt;/clocks&gt;
      &lt;clocks type=&quot;sto.Event&quot; uuid=&quot;77454e62-a0d2-4d0b-b89b-f4568e11d151&quot;&gt;
        &lt;eventType&gt;PARAMETER_CHANGE_EVENT&lt;/eventType&gt;
        &lt;cNum&gt;1&lt;/cNum&gt;
        &lt;clockType&gt;Event&lt;/clockType&gt;
        &lt;identifier&gt;ParameterChangeEvent&lt;/identifier&gt;
        &lt;rates type=&quot;sto.ModelWideEventRate&quot; uuid=&quot;e1ff2228-0ddc-4695-82cd-488c416797c1&quot;&gt;
          &lt;clockId&gt;ParameterChangeEvent&lt;/clockId&gt;
          &lt;rateIdx&gt;-1&lt;/rateIdx&gt;
          &lt;taskId&gt;ModelWideParameterChangeEvent&lt;/taskId&gt;
          &lt;useForExecution&gt;NotForExecution&lt;/useForExecution&gt;
          &lt;rateSpec type=&quot;sto.RateSpec&quot; uuid=&quot;87e2e471-2c1c-4c2e-b0e9-643b3770a2cd&quot;&gt;
            &lt;period&gt;inf&lt;/period&gt;
            &lt;rateType&gt;ModelWideParameterChangeEvent&lt;/rateType&gt;
          &lt;/rateSpec&gt;
        &lt;/rates&gt;
      &lt;/clocks&gt;
      &lt;timeAdvanceMode&gt;FixedStep&lt;/timeAdvanceMode&gt;
    &lt;/clockRegistry&gt;
    &lt;taskRegistry type=&quot;sto.TaskRegistry&quot; uuid=&quot;6c84dd83-0a8d-41ac-a227-91192b672bbd&quot;&gt;
      &lt;rootTaskHierarchyElements type=&quot;sto.Task&quot; uuid=&quot;8d7ca548-0607-4d93-9ee1-690c346e9f78&quot;&gt;
        &lt;isExplicit&gt;true&lt;/isExplicit&gt;
        &lt;rates type=&quot;sto.ModelWideEventRate&quot; uuid=&quot;b08c43a4-acfe-44c8-978c-2598d9e176ac&quot;&gt;
          &lt;clockId&gt;ParameterChangeEvent&lt;/clockId&gt;
          &lt;rateIdx&gt;-1&lt;/rateIdx&gt;
          &lt;taskId&gt;ModelWideParameterChangeEvent&lt;/taskId&gt;
          &lt;useForExecution&gt;NotForExecution&lt;/useForExecution&gt;
          &lt;rateSpec type=&quot;sto.RateSpec&quot; uuid=&quot;3072a961-93c9-4a6f-b3f4-17e3fe240261&quot;&gt;
            &lt;period&gt;inf&lt;/period&gt;
            &lt;rateType&gt;ModelWideParameterChangeEvent&lt;/rateType&gt;
          &lt;/rateSpec&gt;
        &lt;/rates&gt;
        &lt;schedulingClockId&gt;ParameterChangeEvent&lt;/schedulingClockId&gt;
        &lt;timeKeeperClockId&gt;HT09_Linear_Vehicle_Model::defaultTimer&lt;/timeKeeperClockId&gt;
        &lt;elementType&gt;Task&lt;/elementType&gt;
        &lt;identifier&gt;ModelWideParameterChangeEvent&lt;/identifier&gt;
        &lt;priority&gt;-1&lt;/priority&gt;
      &lt;/rootTaskHierarchyElements&gt;
      &lt;rootTaskHierarchyElements type=&quot;sto.Task&quot; uuid=&quot;05e7e045-cbc2-47c8-8548-26a74b8c6407&quot;&gt;
        &lt;isExecutable&gt;true&lt;/isExecutable&gt;
        &lt;orderIndex&gt;1&lt;/orderIndex&gt;
        &lt;rates type=&quot;sto.ClassicPeriodicDiscreteRate&quot; uuid=&quot;35bdc4a4-8f08-4547-af6f-61b2f4832df4&quot;&gt;
          &lt;annotation&gt;D1&lt;/annotation&gt;
          &lt;clockId&gt;HT09_Linear_Vehicle_Model::defaultTimer&lt;/clockId&gt;
          &lt;description&gt;Discrete 1&lt;/description&gt;
          &lt;taskId&gt;_task0&lt;/taskId&gt;
          &lt;rateSpec type=&quot;sto.RateSpec&quot; uuid=&quot;79a13882-68fe-443e-8d7d-805e19c3f3a1&quot;&gt;
            &lt;period&gt;.001&lt;/period&gt;
            &lt;rateType&gt;ClassicPeriodicDiscrete&lt;/rateType&gt;
          &lt;/rateSpec&gt;
        &lt;/rates&gt;
        &lt;schedulingClockId&gt;HT09_Linear_Vehicle_Model::defaultTimer&lt;/schedulingClockId&gt;
        &lt;timeKeeperClockId&gt;HT09_Linear_Vehicle_Model::defaultTimer&lt;/timeKeeperClockId&gt;
        &lt;elementType&gt;Task&lt;/elementType&gt;
        &lt;identifier&gt;_task0&lt;/identifier&gt;
        &lt;priority&gt;40&lt;/priority&gt;
      &lt;/rootTaskHierarchyElements&gt;
      &lt;taskDependencyGraph type=&quot;sto.SerializedTaskConnectionList&quot; uuid=&quot;e11994e0-3a12-4bb7-bd35-d9a47de75f61&quot;&gt;
        &lt;clockIdentifier&gt;HT09_Linear_Vehicle_Model::defaultTimer&lt;/clockIdentifier&gt;
        &lt;taskIdentifier&gt;_task0&lt;/taskIdentifier&gt;
      &lt;/taskDependencyGraph&gt;
      &lt;taskDependencyGraph type=&quot;sto.SerializedTaskConnectionList&quot; uuid=&quot;9b947f8b-6a41-4e86-bae2-474d7648ef04&quot;&gt;
        &lt;clockIdentifier&gt;ParameterChangeEvent&lt;/clockIdentifier&gt;
        &lt;taskIdentifier&gt;ModelWideParameterChangeEvent&lt;/taskIdentifier&gt;
      &lt;/taskDependencyGraph&gt;
      &lt;taskPriorityDirection&gt;HighNumberLast&lt;/taskPriorityDirection&gt;
    &lt;/taskRegistry&gt;
  &lt;/sto.Registry&gt;
&lt;/slexec_sto&gt;</timingAndTaskingRegistry>
    <usePortBasedSampleTime>true</usePortBasedSampleTime>
    <userSpecifiedFixedStepSize>.001</userSpecifiedFixedStepSize>
    <zeroInternalMemoryAtStartupUnchecked>true</zeroInternalMemoryAtStartupUnchecked>
    <FMUBlockMap type="ModelRefInfoRepo.FMUBlockInfo" uuid="730c3f92-2e82-47f3-a81d-fb99aff9c403"/>
    <codeGenInfo type="ModelRefInfoRepo.CodeGenInformation" uuid="4311cd2a-2f58-4a2c-a3e8-a863aea5a42b">
      <DWorkTypeName>MdlrefDW_HT09_Linear_Vehicle_Model_T</DWorkTypeName>
    </codeGenInfo>
    <compiledVariantInfos type="ModelRefInfoRepo.CompiledVariantInfoMap" uuid="fa77f86a-797c-4ce7-9e49-906baf323c12"/>
    <configSettingsForConsistencyChecks type="ModelRefInfoRepo.ConfigSettingsForConsistencyChecks" uuid="36399b0a-b5d6-452c-97fb-ceb7fb63cee9">
      <consistentOutportInitialization>true</consistentOutportInitialization>
      <fixedStepSize>.001</fixedStepSize>
      <frameDiagnosticSetting>2</frameDiagnosticSetting>
      <hasHybridSampleTime>true</hasHybridSampleTime>
      <optimizedInitCode>true</optimizedInitCode>
      <signalLoggingSaveFormat>2</signalLoggingSaveFormat>
      <simSIMDOptimization>1</simSIMDOptimization>
      <solverName>FixedStepDiscrete</solverName>
      <solverType>SOLVER_TYPE_FIXEDSTEP</solverType>
      <hardwareSettings type="ModelRefInfoRepo.HardwareSettings" uuid="86115bdc-8d79-456b-bda2-0db9852fd7b6">
        <prodBitPerChar>8</prodBitPerChar>
        <prodBitPerDouble>64</prodBitPerDouble>
        <prodBitPerFloat>32</prodBitPerFloat>
        <prodBitPerInt>32</prodBitPerInt>
        <prodBitPerLong>64</prodBitPerLong>
        <prodBitPerLongLong>64</prodBitPerLongLong>
        <prodBitPerPointer>64</prodBitPerPointer>
        <prodBitPerPtrDiffT>64</prodBitPerPtrDiffT>
        <prodBitPerShort>16</prodBitPerShort>
        <prodBitPerSizeT>64</prodBitPerSizeT>
        <prodEndianess>1</prodEndianess>
        <prodLargestAtomicFloat>1</prodLargestAtomicFloat>
        <prodLargestAtomicInteger>4</prodLargestAtomicInteger>
        <prodLongLongMode>true</prodLongLongMode>
        <prodShiftRight>true</prodShiftRight>
        <prodWordSize>64</prodWordSize>
      </hardwareSettings>
    </configSettingsForConsistencyChecks>
    <controllableInputRatesMap type="ModelRefInfoRepo.VarTsUIDMap" uuid="bf26ec37-cb98-4235-9e3c-839488ad9b26"/>
    <controllableOutputRatesMap type="ModelRefInfoRepo.VarTsUIDMap" uuid="73dc6b0a-47cf-4008-be2f-ca8dc9536f4b"/>
    <dataPortGroup type="ModelRefInfoRepo.DataPortGroup" uuid="744f450e-7617-41b8-8c1b-b6f00d1ef782">
      <compDataInputPorts>0</compDataInputPorts>
      <compDataInputPorts>1</compDataInputPorts>
      <compDataInputPorts>2</compDataInputPorts>
      <compDataInputPorts>3</compDataInputPorts>
      <compDataInputPorts>4</compDataInputPorts>
      <compDataInputPorts>5</compDataInputPorts>
      <compDataInputPorts>6</compDataInputPorts>
      <compDataOutputPorts>0</compDataOutputPorts>
      <compDataOutputPorts>1</compDataOutputPorts>
      <compDataOutputPorts>2</compDataOutputPorts>
      <compDataOutputPorts>3</compDataOutputPorts>
      <compDataOutputPorts>4</compDataOutputPorts>
      <compDataOutputPorts>5</compDataOutputPorts>
      <compDataOutputPorts>6</compDataOutputPorts>
      <compDataOutputPorts>7</compDataOutputPorts>
      <compDataOutputPorts>8</compDataOutputPorts>
      <compDataOutputPorts>9</compDataOutputPorts>
      <dataInputPorts>0</dataInputPorts>
      <dataInputPorts>1</dataInputPorts>
      <dataInputPorts>2</dataInputPorts>
      <dataInputPorts>3</dataInputPorts>
      <dataInputPorts>4</dataInputPorts>
      <dataInputPorts>5</dataInputPorts>
      <dataInputPorts>6</dataInputPorts>
      <dataOutputPorts>0</dataOutputPorts>
      <dataOutputPorts>1</dataOutputPorts>
      <dataOutputPorts>2</dataOutputPorts>
      <dataOutputPorts>3</dataOutputPorts>
      <dataOutputPorts>4</dataOutputPorts>
    </dataPortGroup>
    <expFcnUnconnectedDataPortGroup type="ModelRefInfoRepo.DataPortGroup" uuid="9324286a-dfa8-4727-a37f-e52b38b6c4cc">
      <compDataOutputPorts>1</compDataOutputPorts>
      <compDataOutputPorts>3</compDataOutputPorts>
    </expFcnUnconnectedDataPortGroup>
    <interfaceParameterInfo type="ModelRefInfoRepo.InterfaceParameterInfo" uuid="c32d77ec-bcf8-4f85-befd-52c0019067b6"/>
    <messageInfo type="ModelRefInfoRepo.MessageInformation" uuid="0b75555f-60d6-4e10-9157-588760da44f8"/>
    <methodInfo type="ModelRefInfoRepo.MethodExistenceInfo" uuid="2f2bc834-a52c-4da6-8a8c-1565255a860b"/>
    <periodicEventPortUnsupportedBlockInfo type="ModelRefInfoRepo.PeriodicEventPortUnsupportedBlockInfo" uuid="382f84f9-31a3-4f8d-9aa6-60eef4732b3c"/>
    <portGroupsRequireSameRate type="ModelRefInfoRepo.PortGroupsRequireSameRate" uuid="35a632f9-2853-4436-8b4d-20487b6cb132">
      <DSMPortGroups type="ModelRefInfoRepo.NameToPortGroupIdxVectMap" uuid="5a1dba63-ef5a-42a3-a7b9-839ce977b316"/>
      <GlobalDSMPortGroups type="ModelRefInfoRepo.NameToPortGroupIdxVectMap" uuid="344de559-1d51-4346-b5cd-a4bbfe3ca367"/>
      <mergedPortGroups type="ModelRefInfoRepo.NameToPortGroupIdxVectMap" uuid="ebcb4347-910e-4996-9a46-d5914b1d0e35"/>
    </portGroupsRequireSameRate>
    <rateBasedMdlGlobalDSMRateSpec type="ModelRefInfoRepo.GlobalDSMRateSpecMap" uuid="f85d1744-462c-4af7-93f8-238d5fb5502d"/>
    <rateSpecOfGlobalDSMAccessedByDescExpFcnMdlMap type="ModelRefInfoRepo.GlobalDSMRateSpecMap" uuid="ea0c1504-06bd-4281-9f00-1f4527d35a93"/>
    <rootBlockDiagramInterface type="ci.Model" uuid="cf86740e-4808-42d1-9e8e-4854235d37c9">
      <p_RootComponentInterface type="ci.ComponentInterface" uuid="07a20775-d2a5-4579-83a1-06649d397bad">
        <p_InputPorts type="ci.SignalInterface" uuid="9078323e-74b2-4fca-b60d-98018ea474a3">
          <p_ComputedNumericDimensions>1.0</p_ComputedNumericDimensions>
          <p_ComputedSampleTime>.001</p_ComputedSampleTime>
          <p_ComputedSampleTime>0.0</p_ComputedSampleTime>
          <p_Name>Delta [Deg]</p_Name>
        </p_InputPorts>
        <p_InputPorts type="ci.SignalInterface" uuid="04f90305-d780-43de-afd3-6397de8aaaf7">
          <p_ComputedNumericDimensions>1.0</p_ComputedNumericDimensions>
          <p_ComputedSampleTime>.001</p_ComputedSampleTime>
          <p_ComputedSampleTime>0.0</p_ComputedSampleTime>
          <p_Name>Vx</p_Name>
        </p_InputPorts>
        <p_InputPorts type="ci.SignalInterface" uuid="ff525a5d-8665-48e0-be84-c29e1715f8aa">
          <p_ComputedNumericDimensions>1.0</p_ComputedNumericDimensions>
          <p_ComputedSampleTime>.001</p_ComputedSampleTime>
          <p_ComputedSampleTime>0.0</p_ComputedSampleTime>
          <p_Name>FZ_FL [N]</p_Name>
        </p_InputPorts>
        <p_InputPorts type="ci.SignalInterface" uuid="c0882789-d5d3-4f21-beda-2e0b1afa17d3">
          <p_ComputedNumericDimensions>1.0</p_ComputedNumericDimensions>
          <p_ComputedSampleTime>.001</p_ComputedSampleTime>
          <p_ComputedSampleTime>0.0</p_ComputedSampleTime>
          <p_Name>FZ_FR [N]</p_Name>
        </p_InputPorts>
        <p_InputPorts type="ci.SignalInterface" uuid="7eba1a41-2002-43a4-ba81-02237fe17bb4">
          <p_ComputedNumericDimensions>1.0</p_ComputedNumericDimensions>
          <p_ComputedSampleTime>.001</p_ComputedSampleTime>
          <p_ComputedSampleTime>0.0</p_ComputedSampleTime>
          <p_Name>FZ_RL [N]</p_Name>
        </p_InputPorts>
        <p_InputPorts type="ci.SignalInterface" uuid="5090cb78-0063-4089-bb84-4650867b1fae">
          <p_ComputedNumericDimensions>1.0</p_ComputedNumericDimensions>
          <p_ComputedSampleTime>.001</p_ComputedSampleTime>
          <p_ComputedSampleTime>0.0</p_ComputedSampleTime>
          <p_Name>FZ_RR [N]</p_Name>
        </p_InputPorts>
        <p_InputPorts type="ci.SignalInterface" uuid="6f6ed2b4-68f5-420c-8a2d-52bfe81ce709">
          <p_ComputedNumericDimensions>1.0</p_ComputedNumericDimensions>
          <p_ComputedSampleTime>.001</p_ComputedSampleTime>
          <p_ComputedSampleTime>0.0</p_ComputedSampleTime>
          <p_Name>u_offset</p_Name>
        </p_InputPorts>
        <p_Name>HT09_Linear_Vehicle_Model</p_Name>
        <p_OutputPorts type="ci.SignalInterface" uuid="9a8c4bbd-07ca-43a4-ad49-68611ac10606">
          <p_ComputedNumericDimensions>1.0</p_ComputedNumericDimensions>
          <p_ComputedSampleTime>.001</p_ComputedSampleTime>
          <p_ComputedSampleTime>0.0</p_ComputedSampleTime>
          <p_Name>Linear_Model_Output_Vy</p_Name>
        </p_OutputPorts>
        <p_OutputPorts type="ci.SignalInterface" uuid="c7da4ac6-187c-4883-bae1-0f96f244e8ba">
          <p_ComputedNumericDimensions>1.0</p_ComputedNumericDimensions>
          <p_ComputedSampleTime>inf</p_ComputedSampleTime>
          <p_ComputedSampleTime>0.0</p_ComputedSampleTime>
          <p_Name>Linear_Model_Output_signal2</p_Name>
        </p_OutputPorts>
        <p_OutputPorts type="ci.SignalInterface" uuid="5120d3e8-a706-4ccf-b991-19a542246f67">
          <p_ComputedNumericDimensions>1.0</p_ComputedNumericDimensions>
          <p_ComputedSampleTime>.001</p_ComputedSampleTime>
          <p_ComputedSampleTime>0.0</p_ComputedSampleTime>
          <p_Name>Linear_Model_Output_psi_dot_no_gain</p_Name>
        </p_OutputPorts>
        <p_OutputPorts type="ci.SignalInterface" uuid="23bcfe48-6f8e-40e7-abf7-a4c34d384baf">
          <p_ComputedNumericDimensions>1.0</p_ComputedNumericDimensions>
          <p_ComputedSampleTime>inf</p_ComputedSampleTime>
          <p_ComputedSampleTime>0.0</p_ComputedSampleTime>
          <p_Name>Linear_Model_Output_signal4</p_Name>
        </p_OutputPorts>
        <p_OutputPorts type="ci.SignalInterface" uuid="7da01226-2620-44e1-9191-8fb103b0c196">
          <p_ComputedNumericDimensions>1.0</p_ComputedNumericDimensions>
          <p_ComputedSampleTime>.001</p_ComputedSampleTime>
          <p_ComputedSampleTime>0.0</p_ComputedSampleTime>
          <p_Name>Linear_Model_Output_Alpha_Deg_Front</p_Name>
        </p_OutputPorts>
        <p_OutputPorts type="ci.SignalInterface" uuid="31463be5-f41d-4d32-9a1d-10f080e12d36">
          <p_ComputedNumericDimensions>1.0</p_ComputedNumericDimensions>
          <p_ComputedSampleTime>.001</p_ComputedSampleTime>
          <p_ComputedSampleTime>0.0</p_ComputedSampleTime>
          <p_Name>Linear_Model_Output_Alpha_Deg_Rear</p_Name>
        </p_OutputPorts>
        <p_OutputPorts type="ci.SignalInterface" uuid="1114843e-15b3-4721-8fb4-a9d8b2654289">
          <p_ComputedNumericDimensions>1.0</p_ComputedNumericDimensions>
          <p_ComputedSampleTime>.001</p_ComputedSampleTime>
          <p_ComputedSampleTime>0.0</p_ComputedSampleTime>
          <p_Name>Vy_LM</p_Name>
        </p_OutputPorts>
        <p_OutputPorts type="ci.SignalInterface" uuid="b59945a4-4b72-4e5b-a190-506fc78a03c7">
          <p_ComputedNumericDimensions>1.0</p_ComputedNumericDimensions>
          <p_ComputedSampleTime>.001</p_ComputedSampleTime>
          <p_ComputedSampleTime>0.0</p_ComputedSampleTime>
          <p_Name>Psi_dot_LM [rad/s]</p_Name>
        </p_OutputPorts>
        <p_OutputPorts type="ci.SignalInterface" uuid="f1a9dd38-4e9f-49fd-a769-045542e93adf">
          <p_ComputedNumericDimensions>1.0</p_ComputedNumericDimensions>
          <p_ComputedSampleTime>.001</p_ComputedSampleTime>
          <p_ComputedSampleTime>0.0</p_ComputedSampleTime>
          <p_Name>Psi_dot_LM [deg/s]</p_Name>
        </p_OutputPorts>
        <p_OutputPorts type="ci.SignalInterface" uuid="91212d92-3b05-43ba-8649-cd70bf3a3681">
          <p_ComputedNumericDimensions>1.0</p_ComputedNumericDimensions>
          <p_ComputedSampleTime>.001</p_ComputedSampleTime>
          <p_ComputedSampleTime>0.0</p_ComputedSampleTime>
          <p_Name>Desired Yaw Rate [rad/s]</p_Name>
        </p_OutputPorts>
        <p_Type>ROOT</p_Type>
      </p_RootComponentInterface>
    </rootBlockDiagramInterface>
    <simulinkFunctions type="ModelRefInfoRepo.SimulinkFunctions" uuid="787d84c9-1154-41b3-8a7c-d7d3871f8083">
      <compSimulinkFunctionCatalog></compSimulinkFunctionCatalog>
    </simulinkFunctions>
    <sltpContext type="sltp.mm.core.Context" uuid="dfe52714-2ba4-418c-9f59-e2606e627e82">
      <globalData type="sltp.mm.core.GlobalData" uuid="f6011040-7183-4ad2-8ee1-907087e4d1cd">
        <dataName>portDelta [Deg]</dataName>
        <type>RootInport</type>
      </globalData>
      <globalData type="sltp.mm.core.GlobalData" uuid="d5127d2b-5cfb-47eb-8158-90800817b070">
        <dataName>portDesired Yaw Rate [rad/s]</dataName>
        <type>RootOutport</type>
      </globalData>
      <globalData type="sltp.mm.core.GlobalData" uuid="2f8f3149-add6-4a61-9161-3f8a549d6574">
        <dataName>portFZ_FL [N]</dataName>
        <type>RootInport</type>
      </globalData>
      <globalData type="sltp.mm.core.GlobalData" uuid="2febdd65-f60c-41c6-8393-3dc87f5d9038">
        <dataName>portFZ_FR [N]</dataName>
        <type>RootInport</type>
      </globalData>
      <globalData type="sltp.mm.core.GlobalData" uuid="d855f283-7406-419f-8424-ade6c4e27224">
        <dataName>portFZ_RL [N]</dataName>
        <type>RootInport</type>
      </globalData>
      <globalData type="sltp.mm.core.GlobalData" uuid="955de5b3-f7ff-495e-96ac-896bbb9b5484">
        <dataName>portFZ_RR [N]</dataName>
        <type>RootInport</type>
      </globalData>
      <globalData type="sltp.mm.core.GlobalData" uuid="1c8a4e1d-ca14-49bf-be47-470d8ad0b578">
        <dataName>portLQR Mz</dataName>
        <type>RootOutport</type>
      </globalData>
      <globalData type="sltp.mm.core.GlobalData" uuid="76b391bf-4051-47d4-94fe-47b0c41a972b">
        <dataName>portLinear States</dataName>
        <type>RootOutport</type>
      </globalData>
      <globalData type="sltp.mm.core.GlobalData" uuid="4457b7b4-489f-442c-94f7-45edc32a6f6e">
        <dataName>portLinear_Model_Output_Alpha_Deg_Front</dataName>
        <type>RootOutport</type>
      </globalData>
      <globalData type="sltp.mm.core.GlobalData" uuid="8f5c061a-63cc-426b-9ccd-86edb637bb48">
        <dataName>portLinear_Model_Output_Alpha_Deg_Rear</dataName>
        <type>RootOutport</type>
      </globalData>
      <globalData type="sltp.mm.core.GlobalData" uuid="eba1d4f2-9eca-405e-b656-889c36f36094">
        <dataName>portLinear_Model_Output_Alpha_Front</dataName>
        <type>RootOutport</type>
      </globalData>
      <globalData type="sltp.mm.core.GlobalData" uuid="80999786-2d84-4ecc-a83c-ac3d9f04e35c">
        <dataName>portLinear_Model_Output_Alpha_Rear</dataName>
        <type>RootOutport</type>
      </globalData>
      <globalData type="sltp.mm.core.GlobalData" uuid="1fdff47a-554c-44c5-bccf-298417366d5c">
        <dataName>portLinear_Model_Output_Vy</dataName>
        <type>RootOutport</type>
      </globalData>
      <globalData type="sltp.mm.core.GlobalData" uuid="4228cbff-8967-4f78-8c6c-662c255e0936">
        <dataName>portLinear_Model_Output_Vy [LM]</dataName>
        <type>RootOutport</type>
      </globalData>
      <globalData type="sltp.mm.core.GlobalData" uuid="166cfa05-f753-4f14-ac17-5c07a98e018c">
        <dataName>portLinear_Model_Output_Vy_LM</dataName>
        <type>RootOutport</type>
      </globalData>
      <globalData type="sltp.mm.core.GlobalData" uuid="74281940-94ee-47bb-899e-6f2a70a15ba9">
        <dataName>portLinear_Model_Output_Vy_dot</dataName>
        <type>RootOutport</type>
      </globalData>
      <globalData type="sltp.mm.core.GlobalData" uuid="48da7035-b03b-4672-8356-99e041f24ee7">
        <dataName>portLinear_Model_Output_Yaw Rate [LM]</dataName>
        <type>RootOutport</type>
      </globalData>
      <globalData type="sltp.mm.core.GlobalData" uuid="99331d4b-56ca-4a72-b5a8-5ebc7d0533ae">
        <dataName>portLinear_Model_Output_psi_dot</dataName>
        <type>RootOutport</type>
      </globalData>
      <globalData type="sltp.mm.core.GlobalData" uuid="d6363d70-5b8f-4b76-a613-c3d80525b5b4">
        <dataName>portLinear_Model_Output_psi_dot [LM]</dataName>
        <type>RootOutport</type>
      </globalData>
      <globalData type="sltp.mm.core.GlobalData" uuid="76852b5a-0bf2-4ff4-a020-5e2b8899c0b9">
        <dataName>portLinear_Model_Output_psi_dot_LM</dataName>
        <type>RootOutport</type>
      </globalData>
      <globalData type="sltp.mm.core.GlobalData" uuid="02eb8839-60cc-4457-b943-ad17de01a7bc">
        <dataName>portLinear_Model_Output_psi_dot_dot</dataName>
        <type>RootOutport</type>
      </globalData>
      <globalData type="sltp.mm.core.GlobalData" uuid="6fee3026-5ead-4b3a-9189-98d14568262d">
        <dataName>portLinear_Model_Output_psi_dot_no_gain</dataName>
        <type>RootOutport</type>
      </globalData>
      <globalData type="sltp.mm.core.GlobalData" uuid="f3658f7d-fddb-438e-9723-a9f3b3a60c85">
        <dataName>portLinear_Model_Output_signal2</dataName>
        <type>RootOutport</type>
      </globalData>
      <globalData type="sltp.mm.core.GlobalData" uuid="667013b6-3dd9-43a5-b1b9-c1531b10ac7f">
        <dataName>portLinear_Model_Output_signal3_Front</dataName>
        <type>RootOutport</type>
      </globalData>
      <globalData type="sltp.mm.core.GlobalData" uuid="7da05528-1831-48bd-bb16-2e8c6007b418">
        <dataName>portLinear_Model_Output_signal3_Rear</dataName>
        <type>RootOutport</type>
      </globalData>
      <globalData type="sltp.mm.core.GlobalData" uuid="b179fff5-1ed6-4fa6-83bd-ae240ba5665c">
        <dataName>portLinear_Model_Output_signal4</dataName>
        <type>RootOutport</type>
      </globalData>
      <globalData type="sltp.mm.core.GlobalData" uuid="6767a6d1-dd6a-4731-a4d4-ac9acb899ee9">
        <dataName>portPsi_dot_LM [deg/s]</dataName>
        <type>RootOutport</type>
      </globalData>
      <globalData type="sltp.mm.core.GlobalData" uuid="fe50827b-63b5-4ca7-ab00-0430b7dfe450">
        <dataName>portPsi_dot_LM [rad/s]</dataName>
        <type>RootOutport</type>
      </globalData>
      <globalData type="sltp.mm.core.GlobalData" uuid="fb8c4549-7a20-4330-8d58-474f1543ae7a">
        <dataName>portVx</dataName>
        <type>RootInport</type>
      </globalData>
      <globalData type="sltp.mm.core.GlobalData" uuid="d281dd05-2e3a-49c9-b889-3b2f8a035945">
        <dataName>portVy_LM</dataName>
        <type>RootOutport</type>
      </globalData>
      <globalData type="sltp.mm.core.GlobalData" uuid="f76dc9d8-81b7-4fb7-abe8-2b760d41a8d2">
        <dataName>portu_offset</dataName>
        <type>RootInport</type>
      </globalData>
      <priorityDirection>HighNumberLast</priorityDirection>
      <unusedTaskIds>1</unusedTaskIds>
      <defaultEventBehavior type="sltp.mm.core.EventBehavior" uuid="be98ebe9-1444-471a-96e6-d42fc4e0af41"/>
      <editorState type="sltp.mm.core.EditorState" uuid="7008c4fd-bedc-4ad0-86d4-61321463f40a">
        <isSynchronized>true</isSynchronized>
        <panelState type="sltp.mm.core.EditorPanelState" uuid="f1ee26e2-d960-4594-8245-b3de54cae991"/>
      </editorState>
      <rootTask type="sltp.mm.core.Task" uuid="20d47778-15c8-4758-81cf-735d1a86a846">
        <context type="sltp.mm.core.Context" uuid="dfe52714-2ba4-418c-9f59-e2606e627e82"/>
        <explicit>false</explicit>
        <name>Default</name>
        <priority>-2147483648</priority>
        <subgraph type="sltp.mm.core.Graph" uuid="969aacd6-a6ed-44bf-8e9b-2d4d74179a9c">
          <tasks type="sltp.mm.core.Task" uuid="381b073d-39c8-4d1e-a4b6-318037a2b7f2">
            <context type="sltp.mm.core.Context" uuid="dfe52714-2ba4-418c-9f59-e2606e627e82"/>
            <explicit>false</explicit>
            <id>2</id>
            <isTimed>true</isTimed>
            <name>D1</name>
            <priority>40</priority>
            <rates type="sltp.mm.core.Rate" uuid="5688c114-ffa3-43df-9144-e59b6a40fac6">
              <annotation>D1</annotation>
              <color>-12240129</color>
              <hasBlocks>true</hasBlocks>
              <identifier>ClassicPeriodicDiscrete0.0010</identifier>
              <rateIndex>0</rateIndex>
              <rateSpec type="sltp.mm.core.RateSpec">
                <period>.001</period>
              </rateSpec>
              <sti>0</sti>
            </rates>
          </tasks>
        </subgraph>
      </rootTask>
    </sltpContext>
    <stateWriterToOwnerMap type="ModelRefInfoRepo.StateWriterInfo" uuid="dbdc5a47-000d-4575-a6ce-01ff7b5d7f13"/>
    <stoClientDataRegistry type="sto.ClientDataRegistry" uuid="02b38ffc-ea97-47c2-bf87-5e197565d755">
      <dataSets type="sto.ClientClockNamedDataSet" uuid="bc792454-de73-483e-8749-a20a4b918ebb">
        <tag>sltpEvents</tag>
      </dataSets>
      <dataSets type="sto.ClientTaskHierarchyElementNamedDataSet" uuid="63cf5cb4-12de-4b4e-9f94-3c2b3b5656d1">
        <tag>sltpTaskGroups</tag>
      </dataSets>
      <dataSets type="sto.ClientTaskHierarchyElementNamedDataSet" uuid="58082964-1a51-4885-80df-abc12eab84dd">
        <dSet type="ModelRefInfoRepo.SltpTaskData" uuid="9b6c6723-b248-4471-abac-c8d1ec062181"/>
        <tSet type="ModelRefInfoRepo.SltpTaskData" uuid="9b6c6723-b248-4471-abac-c8d1ec062181">
          <dataName>D1</dataName>
          <linkedSet type="sto.ClientTaskHierarchyElementNamedDataSet" uuid="58082964-1a51-4885-80df-abc12eab84dd"/>
          <id type="sto.TaskHierarchyElementId">
            <clockId>HT09_Linear_Vehicle_Model::defaultTimer</clockId>
            <id>_task0</id>
          </id>
        </tSet>
        <tag>sltpTasks</tag>
      </dataSets>
    </stoClientDataRegistry>
    <varTsUIDMap type="ModelRefInfoRepo.VarTsUIDMap" uuid="ff09e036-b895-4aae-a5d2-f8358572a591"/>
  </ModelRefInfoRepo.ModelRefInfoRoot>
</MF0>